pyroomacoustics/__init__.py
pyroomacoustics/acoustics.py
pyroomacoustics/beamforming.py
pyroomacoustics/build_rir.cpython-312-darwin.so
pyroomacoustics/build_rir.pyx
pyroomacoustics/libroom.cpython-312-darwin.so
pyroomacoustics/metrics.py
pyroomacoustics/multirate.py
pyroomacoustics/parameters.py
pyroomacoustics/recognition.py
pyroomacoustics/room.py
pyroomacoustics/soundsource.py
pyroomacoustics/sync.py
pyroomacoustics/utilities.py
pyroomacoustics/version.py
pyroomacoustics/windows.py
pyroomacoustics/adaptive/__init__.py
pyroomacoustics/adaptive/adaptive_filter.py
pyroomacoustics/adaptive/data_structures.py
pyroomacoustics/adaptive/lms.py
pyroomacoustics/adaptive/rls.py
pyroomacoustics/adaptive/subband_lms.py
pyroomacoustics/adaptive/util.py
pyroomacoustics/bss/__init__.py
pyroomacoustics/bss/auxiva.py
pyroomacoustics/bss/common.py
pyroomacoustics/bss/fastmnmf.py
pyroomacoustics/bss/fastmnmf2.py
pyroomacoustics/bss/ilrma.py
pyroomacoustics/bss/sparseauxiva.py
pyroomacoustics/bss/trinicon.py
pyroomacoustics/data/materials.json
pyroomacoustics/data/sofa_files.json
pyroomacoustics/data/sofa/AKG_c480_c414_CUBE.sofa
pyroomacoustics/data/sofa/EM32_Directivity.sofa
pyroomacoustics/data/sofa/mit_kemar_large_pinna.sofa
pyroomacoustics/data/sofa/mit_kemar_normal_pinna.sofa
pyroomacoustics/datasets/__init__.py
pyroomacoustics/datasets/base.py
pyroomacoustics/datasets/cmu_arctic.py
pyroomacoustics/datasets/google_speech_commands.py
pyroomacoustics/datasets/sofa.py
pyroomacoustics/datasets/timit.py
pyroomacoustics/datasets/utils.py
pyroomacoustics/denoise/__init__.py
pyroomacoustics/denoise/iterative_wiener.py
pyroomacoustics/denoise/spectral_subtraction.py
pyroomacoustics/denoise/subspace.py
pyroomacoustics/directivities/__init__.py
pyroomacoustics/directivities/analytic.py
pyroomacoustics/directivities/base.py
pyroomacoustics/directivities/direction.py
pyroomacoustics/directivities/integration.py
pyroomacoustics/directivities/interp.py
pyroomacoustics-0.9.0.dist-info/licenses/LICENSE
pyroomacoustics-0.9.0.dist-info/METADATA
pyroomacoustics-0.9.0.dist-info/WHEEL
pyroomacoustics-0.9.0.dist-info/top_level.txt
pyroomacoustics-0.9.0.dist-info/RECORD
