Metadata-Version: 2.4
Name: pyroomacoustics
Version: 0.9.0
Summary: A simple framework for room acoustics and audio processing in Python.
Home-page: https://github.com/LCAV/pyroomacoustics
Author: Laboratory for Audiovisual Communications, EPFL
Author-email: fakufaku@gmail.ch
License: MIT
Keywords: room acoustics signal processing doa beamforming adaptive
Classifier: Development Status :: 4 - Beta
Classifier: Intended Audience :: Science/Research
Classifier: Intended Audience :: Information Technology
Classifier: Topic :: Scientific/Engineering :: Information Analysis
Classifier: Topic :: Scientific/Engineering :: Physics
Classifier: Topic :: Multimedia :: Sound/Audio :: Speech
Classifier: Topic :: Multimedia :: Sound/Audio :: Analysis
Classifier: License :: OSI Approved :: MIT License
Classifier: Programming Language :: Python :: 3.8
Classifier: Programming Language :: Python :: 3.9
Classifier: Programming Language :: Python :: 3.10
Classifier: Programming Language :: Python :: 3.11
Classifier: Programming Language :: Python :: 3.12
License-File: LICENSE
Requires-Dist: Cython
Requires-Dist: numpy>=1.13.0
Requires-Dist: scipy>=0.18.0
Requires-Dist: pybind11>=2.2
Dynamic: author
Dynamic: author-email
Dynamic: classifier
Dynamic: description
Dynamic: description-content-type
Dynamic: home-page
Dynamic: keywords
Dynamic: license
Dynamic: license-file
Dynamic: requires-dist
Dynamic: summary
